infbot/__init__.py
infbot/logger.py
infbot/version.txt
infbot/common/__init__.py
infbot/common/build_dialog_train_data.py
infbot/common/dialog_state.py
infbot/common/make_init_state.py
infbot/common/parse_story.py
infbot/common/system_action.py
infbot/common/user_action.py
infbot/dpl/__init__.py
infbot/dpl/dpl.py
infbot/dpl/keras_dpl.py
infbot/dpl/keras_model.py
infbot/dst/__init__.py
infbot/dst/dst.py
infbot/dst/keras_dst.py
infbot/dst/keras_model.py
infbot/faq/__init__.py
infbot/faq/faq.py
infbot/nlg/__init__.py
infbot/nlg/nlg.py
infbot/nlu/__init__.py
infbot/nlu/chinese_aug.py
infbot/nlu/crf_slot_filler.py
infbot/nlu/data_to_iob.py
infbot/nlu/keras_crf.py
infbot/nlu/keras_intent.py
infbot/nlu/load_nlu_data.py
infbot/nlu/nlu.py
infbot/nlu/test.py
infbot/nlu/engine/__init__.py
infbot/nlu/engine/crf_slot_filler.py
infbot/nlu/engine/engine_core.py
infbot/nlu/engine/ml_intent_classifier.py
infbot/serve/__init__.py
infbot/serve/__main__.py
infbot/serve/serve.py
infbot/train/__init__.py
infbot/train/__main__.py
infbot/train/dpl.py
infbot/train/dst.py
infbot/train/nlg.py
infbot/train/nlu.py
infbot-0.0.31.dist-info/LICENSE
infbot-0.0.31.dist-info/METADATA
infbot-0.0.31.dist-info/WHEEL
infbot-0.0.31.dist-info/top_level.txt
infbot-0.0.31.dist-info/RECORD
