Metadata-Version: 2.1
Name: infbot
Version: 0.0.31
Summary: NLP tool
Home-page: https://github.com/infinity-future/infbot
Author: infinityfuture
Author-email: infinityfuture@foxmail.com
License: Private
Keywords: bot
Platform: any
Requires-Dist: joblib
Requires-Dist: keras
Requires-Dist: numpy
Requires-Dist: pandas
Requires-Dist: pyyaml
Requires-Dist: scikit-learn
Requires-Dist: scipy
Requires-Dist: sklearn-crfsuite
Requires-Dist: tensorflow
Requires-Dist: tqdm
